ragstar/__init__.py
ragstar/chatbot.py
ragstar/dbt_model.py
ragstar/dbt_project.py
ragstar/documentation_generator.py
ragstar/instructions.py
ragstar/types.py
ragstar/vector_store.py
ragstar-0.2.1.dist-info/LICENSE.md
ragstar-0.2.1.dist-info/METADATA
ragstar-0.2.1.dist-info/WHEEL
ragstar-0.2.1.dist-info/top_level.txt
ragstar-0.2.1.dist-info/RECORD
