Metadata-Version: 2.1
Name: ragstar
Version: 0.2.1
Summary: RAG based LLM chatbot for dbt projects.
Home-page: https://github.com/pragunbhutani/ragstar
Author: Pragun Bhutani
Author-email: bhutani.pragun@gmail.com
License: MIT
Classifier: Intended Audience :: Developers
Classifier: License :: OSI Approved :: MIT License
Classifier: Programming Language :: Python
Classifier: Programming Language :: Python :: 3
Classifier: Programming Language :: Python :: 3.10
Classifier: Programming Language :: Python :: 3.11
Classifier: Operating System :: OS Independent
License-File: LICENSE.md
Requires-Dist: pyyaml
Requires-Dist: typing-extensions
Requires-Dist: chromadb
Requires-Dist: openai
Requires-Dist: pylint
Requires-Dist: sphinx
Requires-Dist: recommonmark
Requires-Dist: sphinx-rtd-theme
